qiskit_qcware/__init__.py
qiskit_qcware/conversions.py
qiskit_qcware/py.typed
qiskit_qcware/qcware_backend.py
qiskit_qcware/qcware_job.py
qiskit_qcware/qcware_provider.py
qiskit_qcware-0.1.1a11.dist-info/WHEEL
qiskit_qcware-0.1.1a11.dist-info/METADATA
qiskit_qcware-0.1.1a11.dist-info/RECORD
