Metadata-Version: 2.1
Name: qiskit-qcware
Version: 0.1.1a11
Summary: A provider for Qiskit providing QCWare Forge services
Author: Vic Putz
Author-email: vic.putz@qcware.com
Requires-Python: >=3.8,<4.0
Classifier: Programming Language :: Python :: 3
Classifier: Programming Language :: Python :: 3.8
Classifier: Programming Language :: Python :: 3.9
Requires-Dist: icontract (>=2.4.1,<3.0.0)
Requires-Dist: qcware (>=4.0,<5.0)
Requires-Dist: qcware-quasar (>=1.0.1,<2.0.0)
Requires-Dist: qcware-transpile (==0.1.1a10)
Requires-Dist: qiskit-terra (>=0.17,<0.18)
